{
    "informable": { 
        "area" : [
        "centre",
        "south",
        "north",
        "east",
        "west"
    ],
        "food" : [
        "turkish",
        "indian",
        "chinese",
        "seafood",
        "italian",
        "british",
        "australasian",
        "australian",
        "asian oriental",
        "thai",
        "vegetarian",
        "modern european",
        "gastropub",
        "south indian",
        "european",
        "portuguese",
        "swiss",
        "crossover",
        "catalan",
        "french",
        "mexican",
        "welsh",
        "korean",
        "tuscan",
        "new zealand",
        "molecular gastronomy",
        "eritrean",
        "british food",
        "the americas",
        "north american",
        "spanish",
        "barbeque",
        "persian",
        "greek",
        "lebanese",
        "vietnamese",
        "belgian",
        "creative",
        "jamaican",
        "scottish",
        "cuban",
        "japanese",
        "sri lankan",
        "light bites",
        "moroccan",
        "latin american",
        "african",
        "basque",
        "modern global",
        "halal",
        "mediterranean",
        "bistro",
        "international",
        "unusual",
        "north indian",
        "modern eclectic",
        "danish",
        "afghan",
        "world",
        "northern european",
        "german",
        "cantonese",
        "irish",
        "romanian",
        "russian",
        "english",
        "corsica",
        "steakhouse",
        "hungarian",
        "singaporean",
        "austrian",
        "venetian",
        "ital",
        "polynesian",
        "kosher",
        "swedish",
        "scandinavian",
        "modern american",
        "christmas",
        "malaysian",
        "north african",
        "brazilian",
        "canapes",
        "caribbean",
        "south african",
        "traditional",
        "indonesian",
        "middle eastern",
        "fusion",
        "polish",
        "asian",
        "not mentionedc",
        "afternoon tea",
        "eastern european",
        "panasian",
        "kor",
        "gastro pub",
        "american",
        "pizza",
        "modern  european",
        "modern english"
    ],
        "pricerange" : [
        "expensive",
        "cheap",
        "moderate"
    ],
        "time": [
        "19:45",
        "13:45",
        "10:15",
        "19:15",
        "11:30",
        "10:30",
        "18:45",
        "13:30",
        "15:00",
        "11:45",
        "12:00",
        "15:15",
        "16:45",
        "15:45",
        "17:15",
        "19:30",
        "14:00",
        "10:45",
        "17:30",
        "16:30",
        "17:00",
        "12:30",
        "18:15",
        "18:00",
        "20:15",
        "12:45",
        "14:15",
        "13:15",
        "10:00",
        "16:00",
        "19:00",
        "12:15",
        "11:00",
        "11:15",
        "15:30",
        "14:30",
        "18:30",
        "14:45",
        "17:45",
        "09:15",
        "09:45",
        "16:15",
        "13:00",
        "20:00",
        "21:00",
        "20:30",
        "20:45",
        "15:45",
        "17:45",
        "09:00",
        "13:10",
        "21:45",
        "08:45",
        "09:30"
    ],
        "day": [
        "thursday",
        "wednesday",
        "friday",
        "monday",
        "sunday",
        "saturday",
        "tuesday",
        "thur"
    ],
        "people":[
        "2",
        "3",
        "1",
        "5",
        "6",
        "4",
        "7",
        "8"
    ],
        "name": [
        "meze bar restaurant",
        "indian",
        "pizza hut city centre",
        "the good luck chinese food takeaway",
        "caffe uno",
        "the gardenia",
        "the oak bistro",
        "sala thong",
        "thanh binh",
        "riverside brasserie",
        "cambri",
        "pizza express",
        "yippee noodle bar",
        "curry prince",
        "midsummer house restaurant",
        "cote",
        "restaurant alimentum",
        "nandos city centre",
        "chiquito restaurant bar",
        "maharajah tandoori restaurant",
        "yu garden",
        "bangkok city",
        "copper kettle",
        "backstreet bistro",
        "the golden curry",
        "don pasquale pizzeria",
        "sesame restaurant and bar",
        "charlie",
        "the cow pizza kitchen and bar",
        "india house",
        "loch fyne",
        "eraina",
        "royal spice",
        "prezzo",
        "curry king",
        "the nirala",
        "curry garden",
        "zizzi cambridge",
        "da vinci pizzeria",
        "jinling noodle bar",
        "la raza",
        "cotto",
        "efes restaurant",
        "taj tandoori",
        "golden wok",
        "charlie chan",
        "kohinoor",
        "bedouin",
        "the cambridge chop house",
        "stazione restaurant and coffee bar",
        "graffiti",
        "pizza hut",
        "la mimosa",
        "city stop",
        "grafton hotel restaurant",
        "pizza hut fen ditton",
        "ba",
        "frankie and bennys",
        "rajmahal",
        "rice boat",
        "the missing sock",
        "the varsity restaurant",
        "panahar",
        "nandos",
        "sitar tandoori",
        "oak bistro",
        "scudamores punt",
        "lovel",
        "anatolia",
        "clowns cafe",
        "gourmet burger kitchen",
        "tandoori palace",
        "ali baba",
        "darrys cookhouse and wine shop",
        "hakka",
        "peking restaurant",
        "de luca cucina and bar",
        "the slug and lettuce",
        "city stop restaurant",
        "kymmoy",
        "cambridge lodge restaurant",
        "tandoori",
        "bloomsbury restaurant",
        "ugly duckling",
        "hk fusion",
        "pizza hut cherry hinton",
        "fitzbillies restaurant",
        "hotel du vin and bistro",
        "no",
        "restaurant two two",
        "dojo noodle bar",
        "fi",
        "the copper kettle",
        "michaelhouse cafe",
        "restaurant one seven",
        "the hotpot",
        "royal standard",
        "lev",
        "the river bar steakhouse and grill",
        "pipasha restaurant",
        "golden curry",
        "saigon city",
        "pizza express fen ditton",
        "little seoul",
        "meghna",
        "saffron brasserie",
        "j restaurant",
        "la margherita",
        "the lucky star",
        "lan hong house",
        "hotpot",
        "ask",
        "the gandhi",
        "cocum",
        "golden house",
        "la tasca",
        "shanghai family restaurant",
        "worth house",
        "wagamama",
        "galleria",
        "lo",
        "travellers rest",
        "mahal of cambridge",
        "archway",
        "molecular gastonomy",
        "european",
        "saint johns chop house",
        "anatolia and efes restaurant",
        "shiraz restaurant",
        "nirala",
        "not metioned",
        "cott",
        "cambridge chop house",
        "bridge",
        "lucky star",
        "clu",
        "tang chinese",
        "the",
        "golden house",
        "rice house",
        "limehouse",
        "clowns",
        "restaurant",
        "parkside pools",
        "the dojo noodle bar",
        "nusha",
        "hobson house",
        "au",
        "curry queen",
        "el shaddai",
        "old school",
        "el",
        "cam",
        "yes",
        "gardenia",
        "fin",
        "efes",
        "slug and lettuce",
        "camboats",
        "missing sock",
        "grafton",
        "nus",
        "cambridge lodge",
        "fitzbillies",
        "hamilton lodge",
        "gastropub",
        "funky",
        "cow pizza",
        "ashley",
        "ros",
        "hobso",
        "kitchen and bar",
        "d",
        "cityr",
        "pipasha",
        "seasame restaurant and bar",
        "the alex",
        "hu",
        "one seven",
        "shanghi family restaurant",
        "cambridge be",
        "dif",
        "margherita",
        "ac",
        "bri",
        "india",
        "adden",
        "ian hong house"
    ]
    }
}
